opticam_dbx/__init__.py
opticam_dbx/cli.py
opticam_dbx/opticam.py
opticam_dbx-0.3.1.dist-info/METADATA
opticam_dbx-0.3.1.dist-info/WHEEL
opticam_dbx-0.3.1.dist-info/entry_points.txt
opticam_dbx-0.3.1.dist-info/top_level.txt
opticam_dbx-0.3.1.dist-info/RECORD
