Metadata-Version: 2.1
Name: opticam-dbx
Version: 0.3.1
Summary: Tool for downloading Opticam surveillance camera videos from Dropbox
Home-page: https://github.com/jannero/opticam-dbx
Author: Janne Rönkkö
Author-email: jroo@iki.fi
License: MIT
Keywords: opticam dropbox surveillace camera cctv
Platform: UNKNOWN
Classifier: Development Status :: 4 - Beta
Classifier: Intended Audience :: End Users/Desktop
Classifier: Intended Audience :: System Administrators
Classifier: License :: OSI Approved :: MIT License
Classifier: Operating System :: OS Independent
Classifier: Programming Language :: Python :: 3.6
Classifier: Topic :: Utilities
Requires-Python: >=3.6
Requires-Dist: dropbox
Requires-Dist: envparse
Requires-Dist: setuptools
